{
  "openapi": "3.1.1",
  "info": {
    "title": "MultiTenants.API | v1",
    "version": "1.0.0"
  },
  "servers": [
    {
      "url": "https://localhost:7262"
    },
    {
      "url": "http://localhost:5072"
    }
  ],
  "paths": {
    "/api/AccountApi/Login": {
      "post": {
        "tags": [
          "AccountApi"
        ],
        "requestBody": {
          "content": {
            "application/json": {
              "schema": {
                "$ref": "#/components/schemas/LoginViewModel"
              }
            },
            "text/json": {
              "schema": {
                "$ref": "#/components/schemas/LoginViewModel"
              }
            },
            "application/*+json": {
              "schema": {
                "$ref": "#/components/schemas/LoginViewModel"
              }
            }
          },
          "required": true
        },
        "responses": {
          "200": {
            "description": "OK"
          }
        }
      }
    },
    "/api/AccountApi/SignUp": {
      "post": {
        "tags": [
          "AccountApi"
        ],
        "requestBody": {
          "content": {
            "application/json": {
              "schema": {
                "$ref": "#/components/schemas/SignUpViewModel"
              }
            },
            "text/json": {
              "schema": {
                "$ref": "#/components/schemas/SignUpViewModel"
              }
            },
            "application/*+json": {
              "schema": {
                "$ref": "#/components/schemas/SignUpViewModel"
              }
            }
          },
          "required": true
        },
        "responses": {
          "200": {
            "description": "OK"
          }
        }
      }
    },
    "/WeatherForecast": {
      "get": {
        "tags": [
          "WeatherForecast"
        ],
        "operationId": "GetWeatherForecast",
        "responses": {
          "200": {
            "description": "OK",
            "content": {
              "text/plain": {
                "schema": {
                  "type": "array",
                  "items": {
                    "$ref": "#/components/schemas/WeatherForecast"
                  }
                }
              },
              "application/json": {
                "schema": {
                  "type": "array",
                  "items": {
                    "$ref": "#/components/schemas/WeatherForecast"
                  }
                }
              },
              "text/json": {
                "schema": {
                  "type": "array",
                  "items": {
                    "$ref": "#/components/schemas/WeatherForecast"
                  }
                }
              }
            }
          }
        }
      }
    }
  },
  "components": {
    "schemas": {
      "LoginViewModel": {
        "required": [
          "userName",
          "email"
        ],
        "type": "object",
        "properties": {
          "userName": {
            "maxLength": 50,
            "minLength": 0,
            "type": "string"
          },
          "email": {
            "type": "string"
          }
        }
      },
      "SignUpViewModel": {
        "required": [
          "userName",
          "email",
          "phoneNumber",
          "password",
          "confirmPassword"
        ],
        "type": "object",
        "properties": {
          "userName": {
            "maxLength": 50,
            "minLength": 0,
            "type": "string"
          },
          "email": {
            "type": "string"
          },
          "phoneNumber": {
            "type": "string"
          },
          "password": {
            "minLength": 6,
            "type": "string"
          },
          "confirmPassword": {
            "type": "string"
          }
        }
      },
      "WeatherForecast": {
        "type": "object",
        "properties": {
          "date": {
            "type": "string",
            "format": "date"
          },
          "temperatureC": {
            "pattern": "^-?(?:0|[1-9]\\d*)$",
            "type": [
              "integer",
              "string"
            ],
            "format": "int32"
          },
          "temperatureF": {
            "pattern": "^-?(?:0|[1-9]\\d*)$",
            "type": [
              "integer",
              "string"
            ],
            "format": "int32"
          },
          "summary": {
            "type": [
              "null",
              "string"
            ]
          }
        }
      }
    }
  },
  "tags": [
    {
      "name": "AccountApi"
    },
    {
      "name": "WeatherForecast"
    }
  ]
}